{
  "basics": {
    "name": "李俊緯 (Lee)",
    "label": "Programmer",
    "picture": "",
    "email": "jessy1092@gmail.com",
    "phone": "",
    "website": "",
    "summary": "",
    "location": {
      "address": "",
      "postalCode": "",
      "city": "",
      "countryCode": "",
      "region": ""
    },
    "profiles": [
      {
        "network": "github",
        "username": "jessy1092",
        "url": "https://github.com/jessy1092"
      },
      {
        "network": "linkedin",
        "username": "jessy1092",
        "url": "https://tw.linkedin.com/in/lee-chun-wei-b507556a"
      },
      {
        "network": "twitter",
        "username": "jessylee1092",
        "url": "https://twitter.com/jessylee1092"
      }
    ]
  },
  "work": [
    {
      "company": "Infortrend",
      "position": "軟韌體工程師",
      "website": "http://www.infortrend.com/tw/Home",
      "startDate": "2013-11-15",
      "endDate": "2016-09-23",
      "summary": "",
      "highlights": [
        "開發 OpenStack Cinder Driver ，使 Infortrend 儲存設備可以透過 iSCSI 或 FC 支援 OpenStack ",
        "架設 Gitlab ，協助導入 CI、git 版本控制，增進團隊開發流程",
        "制定新產品的 Command line tool 架構，加強彈性方便擴展指令，並讓團隊更好協同開發",
        "維護 iSCSI module，幫客人處理 iSCSI protocol 上的問題，須幫忙分析效能瓶頸、定位問題、改善漏洞等等",
        "維護 SNMP module，依客戶需求增加資訊，以便能更好的管理機器，協助支援 SNMPv3",
        "開發 NVMe driver ，使 Infortrend 儲存設備可以支援新一代 SSD"
      ]
    },
    {
      "company": "UMC",
      "position": "Summer Intern",
      "website": "",
      "startDate": "2012-07-01",
      "endDate": "2012-08-31",
      "summary": "",
      "highlights": [
        "Big Data 資料存取之有效解決方案研究計畫，主要在Hadoop平台上處理Big Data，並驗證其可行性。"
      ]
    }
  ],
  "volunteer": [
    {
      "organization": "g0v",
      "position": "Contributor",
      "website": "https://g0v.tw/",
      "startDate": "2013-07-01",
      "endDate": "Now",
      "summary": "g0v.tw 是一個推動資訊透明化的社群，致力於開發公民參與社會的資訊平台與工具。",
      "highlights": [
        "hackfoldr 2.0 維護者之一",
        "g0v summit 2014 與 2016 的票務組組長",
        "參與 g0v 基礎建設 專案",
        "參與 救救食蛇龜 專案"
      ]
    }
  ],
  "education": [
    {
      "institution": "Free Code Camp",
      "area": "Information Technology",
      "studyType": "",
      "startDate": "2016",
      "endDate": "Now",
      "gpa": "",
      "courses": [
        "Front End Development Certification"
      ]
    },
    {
      "institution": "NCTU",
      "area": "Electrical, Electronics and Communications Engineering",
      "studyType": "碩士",
      "startDate": "2011",
      "endDate": "2013",
      "gpa": "",
      "courses": []
    },
    {
      "institution": "NCTU",
      "area": "Electrical, Electronics and Communications Engineering",
      "studyType": "學士",
      "startDate": "2007",
      "endDate": "2011",
      "gpa": "",
      "courses": []
    }
  ],
  "awards": [],
  "projects": [
    {
      "name": "react-semantify",
      "creator": "李俊緯",
      "startDate": "2014-12",
      "endDate": "now",
      "website": "http://jessy1092.github.io/react-semantify/",
      "summary": "整合 react 和 semantic-ui，把 semantic-ui 元件包裝成 react component",
      "highlights": "使用 higher-order component 制定各個 properties，更彈性的處理 semantic-ui class name"
    },
    {
      "name": "wowafrica",
      "creator": "wowafrica",
      "startDate": "2015-05",
      "endDate": "now",
      "website": "https://wowafrica.tw/",
      "summary": "wowAfrica 阿非卡為台灣最完整的非洲資訊平台，我們的願景是搭起台灣與非洲的橋樑，藉由資訊、新聞、整合各方資源及實體活動等推廣方式，豐富我們對於非洲的認識及想像，達成進一步的交流與發展。",
      "highlights": "制定整個網站基礎架構，還有架設測試和發佈的流程，使用 react, webpack, gulp, css-module, flux 開發"
    },
    {
      "name": "Openstack Infortrend Cinder Driver",
      "creator": "Infortrend",
      "startDate": "2015-04",
      "endDate": "2015-08",
      "website": "https://review.openstack.org/#/c/177113/",
      "summary": "Infortrend OpenStack Cinder Driver ，支援透過 iSCSI 或 FC 連結 Infortrend 儲存設備。",
      "highlights": "使用 python 撰寫，獲得 openstack cinder 審核通過成為官方認證的 driver 之一"
    },
    {
      "name": "hackforldr-2.0",
      "creator": "ETBlue",
      "startDate": "2014-06",
      "endDate": "now",
      "website": "http://beta.hackfoldr.org/",
      "summary": "Hackfoldr 是你的黑客公事包，用一個網址就可以和夥伴們分享所有的專案文件！",
      "highlights": "維護者之一，幫忙打造開發和發布的環境，使用 gulp 與 travis-ci"
    },
    {
      "name": "NIME",
      "creator": "李俊緯",
      "startDate": "2016-02",
      "startDate": "now",
      "website": "https://github.com/EasyIME/NIME",
      "summary": "使用 nodejs 開發 windows 輸入法",
      "highlights": "藉由 PCMan 開發的 PIME ，發展 nodejs 的輸入法平台，使用 node-ffi 與 debug"
    }
  ],
  "skills": [
    {
      "name": "前端開發",
      "level": "Junior",
      "keywords": [
        "HTML",
        "CSS",
        "Javascript",
        "React",
        "Webpack",
        "Gulp"
      ]
    },
    {
      "name": "軟韌體開發",
      "level": "Senior",
      "keywords": [
        "iSCSI",
        "SNMP",
        "OpenStack Cinder Driver"
      ]
    }
  ],
  "languages": [
    {
      "language": "中文",
      "fluency": "母語"
    },
    {
      "language": "英文",
      "fluency": "略懂"
    }
  ],
  "interests": [],
  "references": []
}
